{
  "siteName": "AIM Agency",
  "siteDescription": "Profesyonel E-spor Takım Yönetimi ve Danışmanlığı",
  "logo": "/images/logo.png",
  "favicon": "/images/favicon.ico",
  "colors": {
    "primary": "#00ff88",
    "secondary": "#1a1a1a"
  },
  "social": {
    "twitter": "https://twitter.com/aimagency",
    "instagram": "https://instagram.com/aimagency",
    "youtube": "https://youtube.com/@aimagency",
    "discord": "https://discord.gg/aimagency",
    "twitch": "https://twitch.tv/aimagency"
  },
  "contact": {
    "email": "info@aimagency.com",
    "phone": "+90 555 123 4567",
    "address": "İstanbul, Türkiye"
  }
}